mzrandom/__init__.py
mzrandom/mzrandom.py
mzrandom-1.0.1.dist-info/METADATA
mzrandom-1.0.1.dist-info/WHEEL
mzrandom-1.0.1.dist-info/top_level.txt
mzrandom-1.0.1.dist-info/RECORD
