Metadata-Version: 2.1
Name: mzrandom
Version: 1.0.1
Summary: A comprehensive and high-entropy random number generator library.
Home-page: https://github.com/mohammadzarghami/mzrandom
Author: Mohammad Zarghami
Author-email: zamohammad1387@gmail.com
License: MIT
Classifier: Programming Language :: Python :: 3
Classifier: License :: OSI Approved :: MIT License
Classifier: Operating System :: OS Independent
Requires-Python: >=3.6
